[
  {
    "id": 33687,
    "ingredients": [
      "black pepper",
      "onions",
      "bread",
      "extra-virgin olive oil",
      "eggs",
      "salt",
      "butter"
    ],
    "cuisine": null
  },
  {
    "id": 9720,
    "ingredients": [
      "ground black pepper",
      "coarse salt",
      "large eggs",
      "extra-virgin olive oil",
      "unsalted butter",
      "lemon",
      "bread",
      "boneless skinless chicken breasts"
    ],
    "cuisine": null
  },
  {
    "id": 23540,
    "ingredients": [
      "ricotta cheese",
      "tomatoes",
      "italian seasoning",
      "bread",
      "provolone cheese",
      "mayonaise"
    ],
    "cuisine": null
  },
  {
    "id": 32235,
    "ingredients": [
      "pesto",
      "ground black pepper",
      "bread",
      "kosher salt"
    ],
    "cuisine": "italian"
  },
  {
    "id": 48050,
    "ingredients": [
      "butternut squash",
      "dark brown sugar",
      "bread",
      "salt",
      "olive oil",
      "chopped fresh sage",
      "shallots",
      "ground white pepper"
    ],
    "cuisine": "french"
  },
  {
    "id": 13816,
    "ingredients": [
      "baguette",
      "salt",
      "medium shrimp",
      "tomatoes",
      "yellow bell pepper",
      "scallions",
      "bread",
      "dijon mustard",
      "creole seasoning",
      "romaine lettuce",
      "extra-virgin olive oil",
      "reduced fat mayonnaise"
    ],
    "cuisine": "cajun_creole"
  },
  {
    "id": 46030,
    "ingredients": [
      "parmesan cheese",
      "ravioli",
      "marinara sauce",
      "bread",
      "Italian cheese blend"
    ],
    "cuisine": "italian"
  },
  {
    "id": 24965,
    "ingredients": [
      "Spanish olives",
      "parsley",
      "olive oil",
      "bread",
      "hard salami"
    ],
    "cuisine": "spanish"
  },
  {
    "id": 5152,
    "ingredients": [
      "kosher salt",
      "chicken meat",
      "fresh dill",
      "sweet onion",
      "fresh lemon juice",
      "bread",
      "pepper",
      "extra-virgin olive oil",
      "plain yogurt",
      "kirby cucumbers"
    ],
    "cuisine": "greek"
  },
  {
    "id": 8036,
    "ingredients": [
      "ground black pepper",
      "kosher salt",
      "olive oil",
      "bread",
      "grated parmesan cheese"
    ],
    "cuisine": "italian"
  },
  {
    "id": 48954,
    "ingredients": [
      "traditional italian sauce",
      "pepperoni",
      "part-skim ricotta cheese",
      "bread",
      "shredded mozzarella cheese"
    ],
    "cuisine": "italian"
  },
  {
    "id": 26788,
    "ingredients": [
      "bread",
      "sliced turkey",
      "mayonaise",
      "chipotle chile powder",
      "cheddar cheese",
      "cooked bacon",
      "sprouts"
    ],
    "cuisine": "mexican"
  },
  {
    "id": 3636,
    "ingredients": [
      "cherry tomatoes",
      "salt",
      "fresh basil",
      "unsalted butter",
      "bread",
      "olive oil",
      "shredded mozzarella cheese",
      "pepper",
      "part-skim ricotta cheese"
    ],
    "cuisine": "italian"
  },
  {
    "id": 28279,
    "ingredients": [
      "genoa salami",
      "sliced ham",
      "mortadella",
      "mozzarella cheese",
      "olives",
      "bread",
      "provolone cheese"
    ],
    "cuisine": "cajun_creole"
  },
  {
    "id": 4357,
    "ingredients": [
      "fresh basil",
      "sprinkles",
      "bread",
      "deli ham",
      "roasted red peppers",
      "crushed red pepper",
      "spinach leaves",
      "low-fat mayonnaise"
    ],
    "cuisine": "italian"
  },
  {
    "id": 31660,
    "ingredients": [
      "eggs",
      "carrots",
      "shredded cabbage",
      "soy sauce",
      "bread",
      "butter"
    ],
    "cuisine": "korean"
  },
  {
    "id": 35077,
    "ingredients": [
      "bread",
      "brown mustard",
      "shredded mozzarella cheese",
      "broccoli florets",
      "boneless skinless chicken breast halves"
    ],
    "cuisine": "italian"
  },
  {
    "id": 9692,
    "ingredients": [
      "bread",
      "cheese spread",
      "artichok heart marin",
      "pitted kalamata olives",
      "dried oregano",
      "diced tomatoes"
    ],
    "cuisine": "greek"
  },
  {
    "id": 25109,
    "ingredients": [
      "jack",
      "salsa",
      "chicken",
      "bread",
      "basil",
      "onions",
      "butter",
      "oil",
      "cheddar cheese",
      "cilantro",
      "toasted sesame seeds"
    ],
    "cuisine": "mexican"
  },
  {
    "id": 33299,
    "ingredients": [
      "bread",
      "salt",
      "black pepper",
      "white sugar",
      "whole peeled tomatoes",
      "butter"
    ],
    "cuisine": "southern_us"
  },
  {
    "id": 3388,
    "ingredients": [
      "vegetables",
      "ciabatta",
      "focaccia",
      "fresh mozzarella",
      "arugula",
      "bread",
      "salt"
    ],
    "cuisine": "italian"
  },
  {
    "id": 8808,
    "ingredients": [
      "bread",
      "garam masala",
      "salt",
      "tomatoes",
      "capsicum",
      "oil",
      "mustard",
      "seeds",
      "green chilies",
      "tumeric",
      "chili powder",
      "coriander"
    ],
    "cuisine": "indian"
  },
  {
    "id": 31647,
    "ingredients": [
      "eggs",
      "ground black pepper",
      "salt",
      "olive oil",
      "manouri",
      "warm water",
      "large eggs",
      "bread",
      "large egg yolks",
      "extra-virgin olive oil"
    ],
    "cuisine": "greek"
  }
]
